{"nodes": [{"id": "lib_utils_wiki_snippet_ts", "label": "wiki-snippet.ts", "file_type": "code", "source_file": "lib\\utils\\wiki-snippet.ts", "source_location": "L1"}, {"id": "wiki_snippet_getrandomwikisnippet", "label": "getRandomWikiSnippet()", "file_type": "code", "source_file": "lib\\utils\\wiki-snippet.ts", "source_location": "L9"}], "edges": [{"source": "lib_utils_wiki_snippet_ts", "target": "spirits_guide_data", "relation": "imports_from", "confidence": "EXTRACTED", "source_file": "lib\\utils\\wiki-snippet.ts", "source_location": "L1", "weight": 1.0}, {"source": "lib_utils_wiki_snippet_ts", "target": "wiki_snippet_getrandomwikisnippet", "relation": "contains", "confidence": "EXTRACTED", "source_file": "lib\\utils\\wiki-snippet.ts", "source_location": "L9", "weight": 1.0}]}